{
  "generated_at": "2026-05-21T08:11:10.985892+08:00",
  "items": [
    {
      "rank": 1,
      "title": "普京结束访华 乘专机离京",
      "summary": "查看更多>",
      "hot_score": "7809534",
      "detail_url": ""
    },
    {
      "rank": 2,
      "title": "中俄两国联合声明",
      "summary": "2026年5月19日至20日，普京应邀来华开展国事访问，中俄两国元首在北京举行会谈。两国发布联合声明，敲定深化全面战略协... 查看更多>",
      "hot_score": "7712861",
      "detail_url": ""
    },
    {
      "rank": 3,
      "title": "关键之年的关键会晤",
      "summary": "5月20日上午，国家主席习近平在北京人民大会堂同来华进行国事访问的俄罗斯总统普京举行会谈。今年是中俄关系的一个关键节点，... 查看更多>",
      "hot_score": "7616889",
      "detail_url": ""
    },
    {
      "rank": 4,
      "title": "小学退回全损雨伞 家委会致歉补款",
      "summary": "近日，苏州市浒墅关中心小学网购45把红色一次性雨伞（总价338.14元）用于运动会，使用后全部损坏并标注学生姓名后退货。... 查看更多>",
      "hot_score": "7521358",
      "detail_url": ""
    },
    {
      "rank": 5,
      "title": "“把媳妇孩子扔了吧”景区标语玩砸了",
      "summary": "近日，河南郑州伏羲山景区一块写有“把孩子扔了吧”“把媳妇扔了吧”等内容的标语牌引发争议。景区回应称，本意是缓解游客爬山压... 查看更多>",
      "hot_score": "7423630",
      "detail_url": ""
    },
    {
      "rank": 6,
      "title": "全世界第二信任豆包的人出现了",
      "summary": "全世界第二信任豆包的人出现了。一位网友用豆包预约餐厅，豆包信誓旦旦地表示：“已占座，已取号”，结果到店后，店员说没有预订... 查看更多>",
      "hot_score": "7333652",
      "detail_url": ""
    },
    {
      "rank": 7,
      "title": "今日小满 万物小得盈满",
      "summary": "5月21日，我们迎来了二十四节气中的第八个节气，也是夏季的第二个节气——小满。愿健康常驻身旁，一生安稳圆满！ 查看更多>",
      "hot_score": "7235470",
      "detail_url": ""
    },
    {
      "rank": 8,
      "title": "机器人穿上皮肤 正处在爆发前夜",
      "summary": "电子皮肤可赋予机器人触觉感知能力，助力其精准作业、保障人机交互安全。如今行业资本涌入，众多企业加紧布局，技术持续迭代，应... 查看更多>",
      "hot_score": "7139399",
      "detail_url": ""
    },
    {
      "rank": 9,
      "title": "《新华字典》盗版销量竟超过正版",
      "summary": "据报道，《新华字典》等商务印书馆核心工具书的盗版销量远大于正版，经济损失巨大。除了畅销书，教材教辅也是盗版重灾区。商务印... 查看更多>",
      "hot_score": "7048794",
      "detail_url": ""
    },
    {
      "rank": 10,
      "title": "夫妻车祸离世 留下120万让两亲家反目",
      "summary": "一场突如其来的车祸，夺走了一对年轻夫妻的生命，男方母亲高阿姨还没从“白发人送黑发人”的悲痛中缓过神，一笔120万元的款项... 查看更多>",
      "hot_score": "6945594",
      "detail_url": ""
    },
    {
      "rank": 11,
      "title": "重庆渝中游轮码头电缆自燃系谣言",
      "summary": "近日，有网民在互联网平台发文称“重庆渝中长滨路一处游轮码头的供电线缆发生自燃”，引发关注。经核实，网传信息系谣言。 查看更多>",
      "hot_score": "6849888",
      "detail_url": ""
    },
    {
      "rank": 12,
      "title": "第一批丁克住医院 关键时刻谁来签字",
      "summary": "近日，“第一批丁克住医院谁来签字”话题引发讨论。有人因无配偶子女，手术时只能临时联系朋友或远亲代签，也有人因医院坚持直系... 查看更多>",
      "hot_score": "6751366",
      "detail_url": ""
    },
    {
      "rank": 13,
      "title": "百万粉丝女网红上厕所被偷拍",
      "summary": "近日，一名拥有百万粉丝的女网红发律师声明称，自己在成都网红饮品店“日落甜茶·莉莉岛”厕所内遭针孔摄像头偷拍，引发关注。涉... 查看更多>",
      "hot_score": "6665611",
      "detail_url": ""
    },
    {
      "rank": 14,
      "title": "12306回应女童座位与母亲隔8节车厢",
      "summary": "5月20日，12306回应“3岁女童高铁座位与母亲相隔8节车厢”一事称，系统按候补规则兑现车票时，仅剩两张不相邻座位。随... 查看更多>",
      "hot_score": "6562018",
      "detail_url": ""
    },
    {
      "rank": 15,
      "title": "英伟达公布强劲财报 全面超预期",
      "summary": "美东时间周三盘后，英伟达公布了其第一财季业绩，不仅营收和利润均超出分析师预期，并且对第二财季的展望也优于预期。在财报发布... 查看更多>",
      "hot_score": "6463401",
      "detail_url": ""
    },
    {
      "rank": 16,
      "title": "520民政局女生现场紧急为男友补妆",
      "summary": "5月20日，北京西城民政局迎来领证热潮。在排队等候的人群中，一对新人的互动格外甜蜜：女生拿出随身携带的化妆品，为男友整理... 查看更多>",
      "hot_score": "6382232",
      "detail_url": ""
    },
    {
      "rank": 17,
      "title": "小满节气到了 那大满去哪了",
      "summary": "小满节气到了，那大满去哪了？原来，在古人看来，满招损，盈不可久。“小满”，才是人生的最高境界！ 查看更多>",
      "hot_score": "6277153",
      "detail_url": ""
    },
    {
      "rank": 18,
      "title": "官方通报福建漳州“泡药杨梅”事件",
      "summary": "漳州通报泡药杨梅事件，当地迅速开展联合执法，查处多家涉事收购点，追回并销毁问题杨梅与违规添加剂，行政立案12起，刑事立案... 查看更多>",
      "hot_score": "6188039",
      "detail_url": ""
    },
    {
      "rank": 19,
      "title": "520当天 国家发改委干了两件大事",
      "summary": "5月20日是民营经济促进法实施一周年，国家发改委推出两项举措。其一召开民营企业座谈会，听取多家企业对经济形势与政策落实的... 查看更多>",
      "hot_score": "6085281",
      "detail_url": ""
    },
    {
      "rank": 20,
      "title": "美股三大指数收涨超1% CPU概念股强势",
      "summary": "美股三大指数集体收涨超1%。纳指涨1.54%，道指涨1.31%，标普500指数涨1.08%。美股CPU概念股表现强势，A... 查看更多>",
      "hot_score": "5983184",
      "detail_url": ""
    },
    {
      "rank": 21,
      "title": "“20岁的年纪60岁的腰”",
      "summary": "当下，不少年轻人因长期久坐办公、低头刷手机，提前出现腰椎健康问题，自嘲“20岁的年纪，60岁的腰”。“这句自嘲真实反映了... 查看更多>",
      "hot_score": "5888561",
      "detail_url": ""
    },
    {
      "rank": 22,
      "title": "国防部回应赖清德“5·20”讲话",
      "summary": "5月20日，国防部发言人回应赖清德相关讲话，直指其借和平说辞宣扬台独，妄图以武谋独、勾结外部势力挑衅。其行径搅动台海局势... 查看更多>",
      "hot_score": "5806834",
      "detail_url": ""
    },
    {
      "rank": 23,
      "title": "杨梅滞留树上 70岁奶奶崩溃哭了",
      "summary": "近日，福建漳州因“泡水杨梅”添加剂事件曝光导致杨梅滞销，70岁果农奶奶因40亩杨梅无人收购，面对树上腐烂的果实崩溃痛哭。... 查看更多>",
      "hot_score": "5694477",
      "detail_url": ""
    },
    {
      "rank": 24,
      "title": "体制内酒店火出圈 年轻人疯抢抢不到",
      "summary": "如今体制内酒店备受年轻人追捧，节假日一房难求。这类住宿区位优越、定价平稳、安全靠谱，契合年轻人理性消费理念。但也存在设施... 查看更多>",
      "hot_score": "5609572",
      "detail_url": ""
    },
    {
      "rank": 25,
      "title": "三星电子工会已推迟罢工",
      "summary": "据报道，三星电子工会已推迟罢工，将于5月23日至5月28日就暂定薪资协议进行投票。 查看更多>",
      "hot_score": "5522665",
      "detail_url": ""
    },
    {
      "rank": 26,
      "title": "歼10CE凭什么吊打欧洲双雄",
      "summary": "2024年卡塔尔“吉扎尔2”联合空中演习中，巴基斯坦空军的歼-10CE与卡塔尔空军的欧洲“台风”战机模拟对抗，以9：0的... 查看更多>",
      "hot_score": "5406450",
      "detail_url": ""
    },
    {
      "rank": 27,
      "title": "年轻人把澡堂子玩成了社交顶配",
      "summary": "近日，汤泉、洗浴中心成不少年轻人的社交新据点，泡汤、汗蒸、自助餐、游戏、过夜“一站式”体验受追捧。有人一年打卡52次花费... 查看更多>",
      "hot_score": "5319247",
      "detail_url": ""
    },
    {
      "rank": 28,
      "title": "藏族民居旁有块100多岁的泰山石敢当",
      "summary": "近日，记者探访位于西藏林芝市工布江达县的太昭古城，发现一块“太山石敢当”石碑。据考证，这块石碑早在清朝时期就被摆放于此。 查看更多>",
      "hot_score": "5230471",
      "detail_url": ""
    },
    {
      "rank": 29,
      "title": "南太行失窃网红松树被偷偷还回来了",
      "summary": "5月20日，河南辉县南太行红旗尖观景台被盗的网红小松树被偷偷还回，但根部严重受损，驴友及村民担忧其难以存活。当地林业部门... 查看更多>",
      "hot_score": "5137234",
      "detail_url": ""
    },
    {
      "rank": 30,
      "title": "成都大学41岁宿管大叔考研上岸",
      "summary": "近日，成都大学41岁宿管师刘明收到了云南财经大学公共管理专业硕士研究生的拟录取通知。作为橙园16栋宿管，他边工作边备考，... 查看更多>",
      "hot_score": "5027924",
      "detail_url": ""
    },
    {
      "rank": 31,
      "title": "520领证爆满：谁说现在没人愿意结婚了",
      "summary": "5月20日上午，在武汉紫阳湖畔的武昌区民政局婚姻登记处，前来办证的新人络绎不绝：排队等候的、静待叫号的、集体宣誓的、打卡... 查看更多>",
      "hot_score": "4943660",
      "detail_url": ""
    },
    {
      "rank": 32,
      "title": "普京对送行人群微笑点头",
      "summary": "5月20日，俄罗斯总统普京结束对中国的国事访问，在北京乘专机离境时向送行人群微笑点头致意。 查看更多>",
      "hot_score": "4835130",
      "detail_url": ""
    },
    {
      "rank": 33,
      "title": "中俄元首会晤成果文件清单",
      "summary": "查看更多>",
      "hot_score": "4740437",
      "detail_url": ""
    },
    {
      "rank": 34,
      "title": "普京离京高清大图",
      "summary": "俄罗斯总统普京5月20日晚结束对中国的国事访问，乘专机离开北京。媒体报道了其离京的高清画面，一起看看！ 查看更多>",
      "hot_score": "4647415",
      "detail_url": ""
    },
    {
      "rank": 35,
      "title": "儿童乳膏涉嫌非法添加：抓获37人",
      "summary": "5月20日，广西平南县通报广西十安生物科技有限公司生产的“消字号”儿童乳膏涉嫌非法添加硝酸咪康唑及虚假宣传，县卫健部门吊... 查看更多>",
      "hot_score": "4564654",
      "detail_url": ""
    },
    {
      "rank": 36,
      "title": "中国的这个“菜园子”实力藏不住了",
      "summary": "云南省作为中国重要的蔬菜生产基地，年外调量超过2000万吨，平均每分钟约40吨蔬菜发往全国150余个大中城市及40多个国... 查看更多>",
      "hot_score": "4451877",
      "detail_url": ""
    },
    {
      "rank": 37,
      "title": "车辆压坏五件瓷器 摊主索赔3万元",
      "summary": "查看更多>",
      "hot_score": "4362118",
      "detail_url": ""
    },
    {
      "rank": 38,
      "title": "被普京抱过的中国男孩回应重逢",
      "summary": "5月20日，曾被普京抱过的中国男孩彭湃回应重逢。他称时隔26年再见格外激动，提及幼时北海公园合影经历，直言普京依旧亲切，... 查看更多>",
      "hot_score": "4275346",
      "detail_url": ""
    },
    {
      "rank": 39,
      "title": "被判赔3家车企共226万 汽车博主回应",
      "summary": "近日，汽车博主“龙哥讲电车”因发布针对比亚迪、赛力斯、小鹏汽车的贬损性不实言论，被三家车企起诉并累计判赔226万元。日前... 查看更多>",
      "hot_score": "4167515",
      "detail_url": ""
    },
    {
      "rank": 40,
      "title": "老人在家里存40万现金被小偷一锅端",
      "summary": "5月18日，浙江丽水遂昌70岁的廖奶奶领回了被盗的40余万元现金。这笔钱是她多年种茶、养猪攒下的积蓄，平时一直藏在家中，... 查看更多>",
      "hot_score": "4077033",
      "detail_url": ""
    },
    {
      "rank": 41,
      "title": "美国起诉古巴革命领袖劳尔·卡斯特罗",
      "summary": "当地时间5月20日，一名美国政府高级官员表示，古巴革命领袖劳尔·卡斯特罗在美国被起诉。此举被认为是美国近期持续加大对古巴... 查看更多>",
      "hot_score": "3986657",
      "detail_url": ""
    },
    {
      "rank": 42,
      "title": "郑丽文：美国从来不支持“台独”",
      "summary": "5月20日，国民党主席郑丽文批评赖清德就职两周年谈话“充满谎言”，并称这是“今年最大的笑话”。郑丽文表示，美国从来不支持... 查看更多>",
      "hot_score": "3895634",
      "detail_url": ""
    },
    {
      "rank": 43,
      "title": "东方甄选前CEO孙东旭直播卖书",
      "summary": "5月20日中午，前东方甄选CEO孙东旭离职半年后，首次在个人账号直播带货，在线两小时，带货数据直接冲上书籍杂志榜第一。 查看更多>",
      "hot_score": "3788952",
      "detail_url": ""
    },
    {
      "rank": 44,
      "title": "家属讲述26年前普京抱中国男孩细节",
      "summary": "5月20日，俄罗斯总统普京在人民大会堂与2000年在北海公园合影的中国男孩彭湃再次见面，两人握手问好。彭湃的父亲回忆当年... 查看更多>",
      "hot_score": "3697550",
      "detail_url": ""
    },
    {
      "rank": 45,
      "title": "美军“尼米兹”号航母进入加勒比海",
      "summary": "美军南方司令部20日在社交媒体发布消息说，美军“尼米兹”号航空母舰战斗群已进入加勒比海。消息说，随同“尼米兹”号航母进入... 查看更多>",
      "hot_score": "3599775",
      "detail_url": ""
    },
    {
      "rank": 46,
      "title": "普京登机前向送行人员挥手点头致意",
      "summary": "5月20日晚，俄罗斯总统普京结束对中国的国事访问，在北京乘专机离境时向送行人群微笑点头并挥手致意，现场解放军三军仪仗队列... 查看更多>",
      "hot_score": "3501642",
      "detail_url": ""
    },
    {
      "rank": 47,
      "title": "足迹疑为东北虎 风险区群众收到提醒",
      "summary": "近日，哈尔滨尚志市发现疑似东北虎神秘脚印，当地划定风险区域劝导民众尽量减少外出，相关部门已迅速进山实地排查核实情况。 查看更多>",
      "hot_score": "3406472",
      "detail_url": ""
    },
    {
      "rank": 48,
      "title": "公共场所亲热尺度怎样才算越界",
      "summary": "公共场所亲热该如何把握尺度？牵手、轻轻拥抱、贴面浅吻都属于正常亲昵举止；长时间深吻、过分搂抱及肢体纠缠则容易逾越边界，主... 查看更多>",
      "hot_score": "3292355",
      "detail_url": ""
    },
    {
      "rank": 49,
      "title": "同样米粉“本地人7元游客13元”",
      "summary": "近日，网友反映阳朔县个别米粉店同样米粉“本地人7元游客13元”，阳朔县市场监管局第一时间介入核查。经查，该店涉嫌区别对待... 查看更多>",
      "hot_score": "3219814",
      "detail_url": ""
    },
    {
      "rank": 50,
      "title": "不放过问题杨梅 不冤枉清白水果",
      "summary": "连日来，福建漳州“泡药杨梅”事件持续发酵。当地迅速成立专班开展全面调查，目前，问题杨梅以及违规添加剂已被查封销毁。民以食... 查看更多>",
      "hot_score": "3123394",
      "detail_url": ""
    }
  ]
}